Workbook

Sheet Dashboard
A1: Essentials Catalog Readiness
A3: Approved baseline | B3: 2BR / 2BA · sleeps 6 · warm modern
A5: Metric | B5: Value | D5: Room | E5: Seed Cost | F5: Target Low | G5: Target High | H5: Current Signal
A6: Seed product lines | B6: =COUNTA('Catalog Review'!$A$5:$A$114) -> 110 | D6: Living Room | E6: =SUMIF('Catalog Review'!$B$5:$B$114,D6,'Catalog Review'!$H$5:$H$114) -> 1646.59 | F6: 2600 | G6: 3100 | H6: =IF(E6=0,"Not yet sourced",IF(E6<F6,"Below standard",IF(E6>G6,"Over target","In range"))) -> Below standard
A7: Seed extended cost | B7: =SUM('Catalog Review'!$H$5:$H$114) -> 5745.23 | D7: Bedrooms | E7: =SUMIF('Catalog Review'!$B$5:$B$114,D7,'Catalog Review'!$H$5:$H$114) -> 2254.64 | F7: 3400 | G7: 4200 | H7: =IF(E7=0,"Not yet sourced",IF(E7<F7,"Below standard",IF(E7>G7,"Over target","In range"))) -> Below standard
A8: Items needing retailer/spec replacement | B8: =COUNTIF('Catalog Review'!$J$5:$J$114,"Replace retailer")+COUNTIF('Catalog Review'!$J$5:$J$114,"Replace specification") -> 0 | D8: Dining | E8: =0 -> 0 | F8: 1000 | G8: 1300 | H8: =IF(E8=0,"Not yet sourced",IF(E8<F8,"Below standard",IF(E8>G8,"Over target","In range"))) -> Not yet sourced
A9: Incomplete source lines | B9: =COUNTIF('Catalog Review'!$J$5:$J$114,"Incomplete") -> 0 | D9: Kitchen | E9: =SUMIF('Catalog Review'!$B$5:$B$114,D9,'Catalog Review'!$H$5:$H$114) -> 949.92 | F9: 900 | G9: 1150 | H9: =IF(E9=0,"Not yet sourced",IF(E9<F9,"Below standard",IF(E9>G9,"Over target","In range"))) -> In range
A10: Open sourcing gaps | B10: =COUNTIF('Gap Register'!$H$4:$H$17,"<>Approved") -> 14 | D10: Bathrooms | E10: =SUMIF('Catalog Review'!$B$5:$B$114,D10,'Catalog Review'!$H$5:$H$114) -> 620.3 | F10: 600 | G10: 800 | H10: =IF(E10=0,"Not yet sourced",IF(E10<F10,"Below standard",IF(E10>G10,"Over target","In range"))) -> In range
D11: Workspace | E11: =0 -> 0 | F11: 400 | G11: 600 | H11: =IF(E11=0,"Not yet sourced",IF(E11<F11,"Below standard",IF(E11>G11,"Over target","In range"))) -> Not yet sourced
D12: Entry / Shared | E12: =0 -> 0 | F12: 400 | G12: 600 | H12: =IF(E12=0,"Not yet sourced",IF(E12<F12,"Below standard",IF(E12>G12,"Over target","In range"))) -> Not yet sourced
D13: Delivery | E13: =0 -> 0 | F13: 700 | G13: 1000 | H13: =IF(E13=0,"Not yet sourced",IF(E13<F13,"Below standard",IF(E13>G13,"Over target","In range"))) -> Not yet sourced
A15: How to use: review each Catalog Review line, choose a Review Status, replace legacy retailers/specifications, and source each Gap Register requirement. Revalidate prices, availability, variants, return policies, delivery, and TV/mount compatibility before procurement.

Sheet Catalog Review
A1: Luxe Haven Essentials — Catalog Review
A2: Seeded from Todd Furniture Calculator (1).xlsx. Prices and availability are unverified source values until reviewed.
A4: Product ID | B4: Room | C4: Category | D4: Item | E4: Retailer | F4: Quantity | G4: Unit Price | H4: Extended Cost | I4: Priority | J4: Source Status | K4: Review Status | L4: Procurement Class | M4: Supply Treatment | N4: Source URL | O4: Variant / Specifications | P4: Substitution | Q4: Last Verified | R4: Source Row
A5: ESS-0001 | B5: Living Room | C5: Furniture | D5: Coffee Table and Side Table Set | E5: Walmart | F5: 1 | G5: 139.99 | H5: =IF(OR(F5="",G5=""),0,F5*G5) -> 139.99 | I5: Operational | J5: Candidate | K5: Needs review | L5: Furnishing order | M5: Durable furnishing | N5: https://www.walmart.com/ip/Baxluxe-3-Pieces-Living-Room-Coffee-Table-Set-Retro-Coffee-Table-2-Square-End-Tables-Tea-Table-Set-Metal-Frame-Apartment-Home-Office-Gray/17210359637?athAsset=eyJhdGhjcGlkIjoiMTcyMTAzNTk2MzciLCJhdGhzdGlkIjoiQ1M0Nzh%2BQ1MwOTgiLCJhdGhwb3NiIjoiMTYiLCJhdGhhbmNpZCI6IjE2NTIyODczMDQ2IiwiYXRocmsiOjAuMH0=&athena=true&ssp=AMCF&athbdg=L1600 | P5: Not defined | R5: 5
A6: ESS-0002 | B6: Living Room | C6: Technology & Safety | D6: TV stand | E6: Walmart | F6: 1 | G6: 148.94 | H6: =IF(OR(F6="",G6=""),0,F6*G6) -> 148.94 | I6: Operational | J6: Candidate | K6: Needs review | L6: Furnishing order | M6: Durable furnishing | N6: https://www.walmart.com/ip/River-Street-Designs-Sage-52-Metal-Frame-TV-Stand-Natural-Black/444185047?classType=REGULAR | P6: Not defined | R6: 6
A7: ESS-0003 | B7: Dining | C7: Furniture | D7: Dining Table | E7: Wayfair | F7: 1 | G7: 181.99 | H7: =IF(OR(F7="",G7=""),0,F7*G7) -> 181.99 | I7: Launch-critical | J7: Candidate | K7: Needs review | L7: Furnishing order | M7: Durable furnishing | N7: https://www.wayfair.com/furniture/pdp/17-stories-ryota-rectangular-275-l-x-43-w-dining-set-w110029078.html?piid=14641350&auctionId=84e30a44-8542-4147-bb3a-a6ae12168151&trackingId=%7B%22adType%22%3A%22WSP%22%2C%22auctionId%22%3A%2284e30a44-8542-4147-bb3a-a6ae12168151%22%7D&adTypeId=1 | P7: Not defined | R7: 7
A8: ESS-0004 | B8: Living Room | C8: Technology & Safety | D8: Ring Doorbell Kit (wireless) | E8: Amazon | F8: 1 | G8: 150 | H8: =IF(OR(F8="",G8=""),0,F8*G8) -> 150 | I8: Operational | J8: Candidate | K8: Needs review | L8: Furnishing order | M8: Initial setup only | N8: https://www.amazon.com/dp/B09WZBPX7K/?coliid=I3L5N7BZGIHVZW&colid=1M4ZRDEJBTOSI&th=1 | P8: Not defined | R8: 8
A9: ESS-0005 | B9: Living Room | C9: Technology & Safety | D9: Schalge Encode | E9: Amazon | F9: 1 | G9: 265.35 | H9: =IF(OR(F9="",G9=""),0,F9*G9) -> 265.35 | I9: Operational | J9: Candidate | K9: Needs review | L9: Furnishing order | M9: Initial setup only | N9: https://www.amazon.com/dp/B07HXFKMYR/?coliid=I5BG3QRC5EMKU&colid=1M4ZRDEJBTOSI&th=1 | P9: Not defined | R9: 9
A10: ESS-0006 | B10: Living Room | C10: Technology & Safety | D10: TV Mount | E10: Walmart | F10: 1 | G10: 25.26 | H10: =IF(OR(F10="",G10=""),0,F10*G10) -> 25.26 | I10: Launch-critical | J10: Candidate | K10: Needs review | L10: Furnishing order | M10: Initial setup only | N10: https://www.walmart.com/ip/Full-Motion-Articulating-TV-Wall-Mount-Bracket-Swivel-Tilting-Fits-26-65-Inch-Flat-Curved-TVs-Holds-up-to-99lbs/148790691?wmlspartner=wlpa&selectedSellerId=102594905&selectedOfferId=C3BA38E0BCA2329986317E165F8874BC&conditionGroupCode=1&gclsrc=aw.ds&&adid=22222222227C3BA38E0BCA2329986317E165F8874BC_198068869633_23857841887&wl0=&wl1=g&wl2=c&wl3=809139801293&wl4=pla-2483468578281&wl5=9027296&wl6=&wl7=&wl8=&wl9=pla&wl10=5469150719&wl11=online&wl12=C3BA38E0BCA2329986317E165F8874BC&veh=sem&gad_source=1&gad_campaignid=23857841887&gbraid=0AAAABDAnf97DbT-I179GyN1uuWAMb62nN&gclid=Cj0KCQjwm8bTBhDWARIsAC9Hi8lce0YQZUmNpxDX2e9gkBK3LFY_UtxkoHi526hlhVNuNG_bI9quDyUaAokCEALw_wcB | P10: Not defined | R10: 10
A11: ESS-0008 | B11: Living Room | C11: Technology & Safety | D11: 55 inch Smart TV | E11: Walmart | F11: 1 | G11: 198 | H11: =IF(OR(F11="",G11=""),0,F11*G11) -> 198 | I11: Launch-critical | J11: Candidate | K11: Needs review | L11: Furnishing order | M11: Durable furnishing | N11: https://www.walmart.com/ip/Onn-55-4K-UHD-POWERED-BY-nbsp-VIZIO-nbsp-TV/16112057713?classType=REGULAR&athbdg=L1200&from=/search | P11: Not defined | R11: 12
A12: ESS-0009 | B12: Living Room | C12: Textiles | D12: Throw Pillows 20x20 (set of 2) | E12: Walmart | F12: 1 | G12: 15 | H12: =IF(OR(F12="",G12=""),0,F12*G12) -> 15 | I12: Experience | J12: Candidate | K12: Needs review | L12: Furnishing order | M12: Initial setup only | N12: https://www.walmart.com/ip/seot/12769156945?listRegistryId=5b62a874-18a6-4aa7-ae38-49a6da8ee6d7&listRegistryType=WL | P12: Not defined | R12: 13
A13: ESS-0010 | B13: Living Room | C13: Furniture | D13: Sofa | E13: Walmart | F13: 1 | G13: 259.69 | H13: =IF(OR(F13="",G13=""),0,F13*G13) -> 259.69 | I13: Launch-critical | J13: Candidate | K13: Needs review | L13: Furnishing order | M13: Durable furnishing | N13: https://www.walmart.com/ip/Asofer-3-in-1-Convertible-Sofa-Bed-with-Pull-Out-Couch-Storage-Armrests-Adjustable-Backrest-Dark-Gray/18877011143?wmlspartner=wlpa&selectedSellerId=101568055&gclsrc=aw.ds&&adid=2222222222718877011143_101568055_197550293509_23983641304&wl0=&wl1=g&wl2=c&wl3=814384077295&wl4=pla-2488144350671&wl5=9027296&wl6=&wl7=&wl8=&wl9=pla&wl10=5324904963&wl11=online&wl12=18877011143_101568055&veh=sem&gad_source=1&gad_campaignid=23983641304&gbraid=0AAAABDAnf94aVAcpCqC-W5PtSYyUiR2eo&gclid=CjwKCAjwy5rUBhB5EiwAIoAtCsxAQw3ZBOggUWULhGJUDa1NSgNpKNh_Nyvamr5y8lwA7ay0XheN7xoCgTgQAvD_BwE | P13: Not defined | R13: 14
A14: ESS-0011 | B14: Living Room | C14: Lighting | D14: Lamps | E14: Walmart | F14: 1 | G14: 50.39 | H14: =IF(OR(F14="",G14=""),0,F14*G14) -> 50.39 | I14: Operational | J14: Candidate | K14: Needs review | L14: Furnishing order | M14: Initial setup only | N14: https://www.walmart.com/ip/DAYBETTER-Arc-Floor-Lamp-Living-Room-Farmhouse-Lamps-3-Color-Temperatures-Unique-Hanging-Douoble-Drum-Lampshade-Bedroom-Room/18562314755?wmlspartner=wlpa&selectedSellerId=101074895&selectedOfferId=AC99BEB3219931969E2902E1B9242D4B&conditionGroupCode=1&gclsrc=aw.ds&&adid=22222222227AC99BEB3219931969E2902E1B9242D4B_201917097554_24093496471&wl0=&wl1=g&wl2=c&wl3=818958117028&wl4=pla-2480486220622&wl5=9027296&wl6=&wl7=&wl8=&wl9=pla&wl10=422556803&wl11=online&wl12=AC99BEB3219931969E2902E1B9242D4B&veh=sem&gad_source=4&gad_campaignid=24093496471&gbraid=0AAAABDAnf94mVWmpTXiy3-Xrej0PH456t&gclid=CjwKCAjwy5rUBhB5EiwAIoAtCllch-DAs9IcVhvn8dIbXetXuQzGnM0SCw74AYS8Er2tBxuZFyE7YxoCweEQAvD_BwE | P14: Not defined | R14: 15
A15: ESS-0012 | B15: Living Room | C15: Décor | D15: Fake plants | E15: Walmart | F15: 1 | G15: 30.99 | H15: =IF(OR(F15="",G15=""),0,F15*G15) -> 30.99 | I15: Experience | J15: Candidate | K15: Needs review | L15: Furnishing order | M15: Initial setup only | N15: https://www.walmart.com/ip/5FT-Artificial-Ficus-Tree-with-Natural-Wood-Trunk-and-Lifelike-Leaves-Silk-Fake-Potted-Tree-with-Wood-Branches-Faux-Tree-for-Office-Home-Decor/5109329248?wmlspartner=wlpa&selectedSellerId=101078367&selectedOfferId=C62FB8449A9335D38C16FECD521683CE&conditionGroupCode=1&gclsrc=aw.ds&&adid=22222222227C62FB8449A9335D38C16FECD521683CE_186470818946_22924454142&wl0=&wl1=g&wl2=c&wl3=779154776326&wl4=pla-2447080184631&wl5=9027296&wl6=&wl7=&wl8=&wl9=pla&wl10=422569237&wl11=online&wl12=C62FB8449A9335D38C16FECD521683CE&veh=sem&gad_source=1&gad_campaignid=22924454142&gbraid=0AAAABDAnf949hSuxQvhKJuICID3NCGzqU&gclid=CjwKCAjwy5rUBhB5EiwAIoAtCl6pV0E2etwdzaXV12CdG78hb9zfZBq6-wWrRZl6gLTP9w1BVzw3MhoC9jwQAvD_BwE | P15: Not defined | R15: 16
A16: ESS-0013 | B16: Living Room | C16: Textiles | D16: Rugs - Area 8x10 | E16: Amazon | F16: 1 | G16: 89 | H16: =IF(OR(F16="",G16=""),0,F16*G16) -> 89 | I16: Experience | J16: Candidate | K16: Needs review | L16: Furnishing order | M16: Initial setup only | N16: https://www.amazon.com/dp/B0GTTYHLH4/ref=twister_B0G43JPZLX?_encoding=UTF8&th=1 | P16: Not defined | R16: 17
A17: ESS-0014 | B17: Living Room | C17: Décor | D17: Wall Art | E17: Wayfair | F17: 1 | G17: 64.99 | H17: =IF(OR(F17="",G17=""),0,F17*G17) -> 64.99 | I17: Experience | J17: Candidate | K17: Needs review | L17: Furnishing order | M17: Initial setup only | N17: https://www.wayfair.com/decor-pillows/pdp/idea4wall-mid-century-shape-warm-brown-faded-black-abstract-lines-artwork-modern-minimalist-neutral-wall-pictures-framed-canvas-giclee-print-2-pieces-wall-art-16x24x2-pcs-24x36x2-pcs-sfta7516.html?piid=92285705%2C92285706%2C119463642 | P17: Not defined | R17: 18
A18: ESS-0015 | B18: Living Room | C18: Décor | D18: Small Décor | E18: Amazon | F18: 1 | G18: 26.99 | H18: 26.99 | I18: Experience | J18: Candidate | K18: Needs review | L18: Furnishing order | M18: Initial setup only | N18: https://www.amazon.com/Teenyyou-Centerpiece-Decorations-Natural-Decorative/dp/B0DB1WX11X/ref=sr_1_16?crid=2DHFZ951CMSNA&dib=eyJ2IjoiMSJ9.bJuy5ysgscqE-qjq6fpmUugXuBaqd2fFlkCgaTg4MbpHzCBdePwv9_4T2-tPZJHiZNFfWIwPTzhvbvQ5d40N5s5g2np9bm4WYWq77XHungCtvLDKCZwlObM6bTzOyu66ezrfnSxyWXkXIGQwFJKj8izObMrsMKBNg7gYrdx9vJyhlk-wrEvHIQLLh5gsU1v7yP9vhRu2rSL99VSEPVFMzyY3H-j5oFgleixNCO3-xCUJVyUfnEh8asY556q70RiF8nODq9HX37VQqYEwGZP3TWil1DNct-MIoR88pHuM4go.cJJ1unB7fMJypK_Cat83vMy5pdlMpaE1W-pacq6THXQ&dib_tag=se&keywords=bowl%2Bwith%2Bdecorative%2Bball%2Bset&qid=1787286303&sprefix=bowl%2Bwith%2Bdecorative%2Bball%2Bset%2Caps%2C155&sr=8-16&th=1 | P18: Not defined | R18: 19
A19: ESS-0016 | B19: Living Room | C19: Furniture | D19: Accent Chair | E19: Walmart | F19: 1 | G19: 182 | H19: =IF(OR(F19="",G19=""),0,F19*G19) -> 182 | I19: Operational | J19: Candidate | K19: Needs review | L19: Furnishing order | M19: Durable furnishing | N19: https://www.walmart.com/ip/seot/8473020072?listRegistryId=e0137f6c-0e2c-4ff6-803f-31d87046ce07&listRegistryType=WL | P19: Not defined | R19: 20
A20: ESS-0017 | B20: Bedrooms | C20: Furniture | D20: Queen Bed Frame | E20: Amazon | F20: 2 | G20: 154.64 | H20: =IF(OR(F20="",G20=""),0,F20*G20) -> 309.28 | I20: Launch-critical | J20: Candidate | K20: Needs review | L20: Furnishing order | M20: Durable furnishing | N20: https://www.amazon.com/dp/B086M58PQ3/?coliid=I8MFC9QO4PAK4&colid=1VYLQVL2D6O92&th=1 | P20: Not defined | R20: 23
A21: ESS-0018 | B21: Bedrooms | C21: Other | D21: Queen 10 inch Memory Foam | E21: Amazon | F21: 2 | G21: 180 | H21: =IF(OR(F21="",G21=""),0,F21*G21) -> 360 | I21: Operational | J21: Candidate | K21: Needs review | L21: Furnishing order | M21: Durable furnishing | N21: https://www.amazon.com/dp/B0CSJQGDC6/?coliid=I3RMXVUSK9XBCN&colid=1VYLQVL2D6O92&th=1 | P21: Not defined | R21: 24
A22: ESS-0019 | B22: Bedrooms | C22: Technology & Safety | D22: 55 inch Smart TV | E22: Walmart | F22: 2 | G22: 198 | H22: =IF(OR(F22="",G22=""),0,F22*G22) -> 396 | I22: Launch-critical | J22: Candidate | K22: Needs review | L22: Furnishing order | M22: Durable furnishing | N22: https://www.walmart.com/ip/Onn-55-4K-UHD-POWERED-BY-nbsp-VIZIO-nbsp-TV/16112057713?classType=REGULAR&athbdg=L1200&from=/search | P22: Not defined | R22: 25
A23: ESS-0020 | B23: Bedrooms | C23: Technology & Safety | D23: TV Mount | E23: Walmart | F23: 2 | G23: 25.26 | H23: =IF(OR(F23="",G23=""),0,F23*G23) -> 50.52 | I23: Launch-critical | J23: Candidate | K23: Needs review | L23: Furnishing order | M23: Initial setup only | N23: https://www.walmart.com/ip/Full-Motion-Articulating-TV-Wall-Mount-Bracket-Swivel-Tilting-Fits-26-65-Inch-Flat-Curved-TVs-Holds-up-to-99lbs/148790691?wmlspartner=wlpa&selectedSellerId=102594905&selectedOfferId=C3BA38E0BCA2329986317E165F8874BC&conditionGroupCode=1&gclsrc=aw.ds&&adid=22222222227C3BA38E0BCA2329986317E165F8874BC_198068869633_23857841887&wl0=&wl1=g&wl2=c&wl3=809139801293&wl4=pla-2483468578281&wl5=9027296&wl6=&wl7=&wl8=&wl9=pla&wl10=5469150719&wl11=online&wl12=C3BA38E0BCA2329986317E165F8874BC&veh=sem&gad_source=1&gad_campaignid=23857841887&gbraid=0AAAABDAnf97DbT-I179GyN1uuWAMb62nN&gclid=Cj0KCQjwm8bTBhDWARIsAC9Hi8lce0YQZUmNpxDX2e9gkBK3LFY_UtxkoHi526hlhVNuNG_bI9quDyUaAokCEALw_wcB | P23: Not defined | R23: 26
A24: ESS-0021 | B24: Bedrooms | C24: Furniture | D24: Nightstand | E24: Walmart | F24: 2 | G24: 104 | H24: =IF(OR(F24="",G24=""),0,F24*G24) -> 208 | I24: Operational | J24: Candidate | K24: Needs review | L24: Furnishing order | M24: Durable furnishing | N24: https://www.amazon.com/dp/B0FWCRTG82/?coliid=I114SDJDGX8FKY&colid=1VYLQVL2D6O92&ref_=list_c_wl_lv_ov_lig_dp_it&th=1 | P24: Not defined | R24: 27
A25: ESS-0022 | B25: Bedrooms | C25: Furniture | D25: Nightstand Lamp | E25: Lowe's | F25: 2 | G25: 26.59 | H25: =IF(OR(F25="",G25=""),0,F25*G25) -> 53.18 | I25: Operational | J25: Candidate | K25: Needs review | L25: Furnishing order | M25: Initial setup only | N25: https://www.amazon.com/Dreamholder-Bedside-Charging-Holders-Nightstand/dp/B0H378M6XP/ref=sr_1_52?crid=1BLFXHA7EX9N3&dib=eyJ2IjoiMSJ9.wfPbD8qvCSJdIuSibc-aE3ZS6w44Zw3Ybo2drejg6WrIQY-HWusWDzKzQDG1IC9PTbJ1tUMdeAN--oXNsdrSaryE9IaKC6rvdROUkLh3X_NckXoANcdLVCbFnhdER9LCGbZhiAP-RPur2a4fTl6ZGb_gBkqCkGHqV08OGr2pTwn_DfTojUTHnBtxcJm6-Nb2hMwAtAWqbP1wK9tD9iv2qGF9G1usJ0yTdJPd5mDdGoX-Ki-IMYkRV6Qk3NeV3agIwn5kYdVpbMCKW17xIYywx4ONAEiU8VsjytNl4Yk3BNk.7JQE1RYQP7cSQTpBCqE1g6JJOb9ZvBICScLDBCHeKvk&dib_tag=se&keywords=Small%2BTable%2BLamp%2BSet%2BWith%2BUSB%2BA%2BC%2BCharging%2BPorts&nsdOptOutParam=true&qid=1787200065&sprefix=small%2Btable%2Blamp%2Bset%2Bwith%2Busb%2Ba%2Bc%2Bcharging%2Bports%2Caps%2C190&sr=8-52&th=1 | P25: Not defined | R25: 28
A26: ESS-0023 | B26: Bedrooms | C26: Textiles | D26: Blackout Curtains (check room for correct size) | E26: Amazon | F26: 2 | G26: 27.54 | H26: =IF(OR(F26="",G26=""),0,F26*G26) -> 55.08 | I26: Operational | J26: Candidate | K26: Needs review | L26: Furnishing order | M26: Initial setup only | N26: https://www.amazon.com/dp/B09HBXQTLJ/?coliid=I2FDKI5OGXR160&colid=1VYLQVL2D6O92&th=1 | P26: Not defined | R26: 29
A27: ESS-0024 | B27: Bedrooms | C27: Other | D27: Wooden hangers - 20pk | E27: Amazon | F27: 2 | G27: 28.99 | H27: =IF(OR(F27="",G27=""),0,F27*G27) -> 57.98 | I27: Operational | J27: Candidate | K27: Needs review | L27: Furnishing order | M27: Initial setup only | N27: https://www.amazon.com/High-Grade-Hangers-Smooth-Precisely-Camisole/dp/B075FBQB2W/ref=sr_1_1_sspa?crid=FZHEWKOAQ0CU&keywords=wooden+hangers&qid=1671226028&sprefix=wooden+%2Caps%2C664&sr=8-1-spons&psc=1&spLa=ZW5jcnlwdGVkUXVhbGlmaWVyPUEzSUdYSzVQMDJBWUVLJmVuY3J5cHRlZElkPUEwNjM5NzI2M0tUQkFDQ0xOUDlXRCZlbmNyeXB0ZWRBZElkPUEwODI0NTEwMlYwRDJYS1MzMDFBRyZ3aWRnZXROYW1lPXNwX2F0ZiZhY3Rpb249Y2xpY2tSZWRpcmVjdCZkb05vdExvZ0NsaWNrPXRydWU= | P27: Not defined | R27: 30
A28: ESS-0025 | B28: Bedrooms | C28: Textiles | D28: Curtain rod - wrap around (check room for correct size) | E28: Amazon | F28: 2 | G28: 14.97 | H28: =IF(OR(F28="",G28=""),0,F28*G28) -> 29.94 | I28: Operational | J28: Candidate | K28: Needs review | L28: Furnishing order | M28: Initial setup only | N28: https://www.amazon.com/AmazonBasics-Room-Darkening-Curtain-Rod-Bronze/dp/B0792JTC66/ref=sr_1_1_sspa?crid=27WLJUKEZWKD&keywords=curtain%2Brod%2Bwrap%2Baround&qid=1671226100&sprefix=curtain%2Brod%2Bwrap%2Baround%2Caps%2C128&sr=8-1-spons&spLa=ZW5jcnlwdGVkUXVhbGlmaWVyPUEzUEQ3MU5HOTlDRUpZJmVuY3J5cHRlZElkPUEwMTU3MTExMlMyOTY1UUg2V0pNNiZlbmNyeXB0ZWRBZElkPUEwNDQxNzkxVU9QOFBJTVY3SkJUJndpZGdldE5hbWU9c3BfYXRmJmFjdGlvbj1jbGlja1JlZGlyZWN0JmRvTm90TG9nQ2xpY2s9dHJ1ZQ&th=1 | P28: Not defined | R28: 31
A29: ESS-0026 | B29: Bedrooms | C29: Textiles | D29: Utopia Bedding flat sheets 6 pack(Queen Size) | E29: Amazon | F29: 2 | G29: 29.44 | H29: =IF(OR(F29="",G29=""),0,F29*G29) -> 58.88 | I29: Experience | J29: Candidate | K29: Needs review | L29: Furnishing order | M29: Initial and recurring | N29: https://www.amazon.com/Flat-Sheet-White-Brushed-Microfiber/dp/B00XK9CN3U/ref=sr_1_5?crid=1MFHWYB1ZK2TH&keywords=utopia%2Bflat%2Bsheet%2Bset&qid=1671226149&sprefix=utopia%2Bflat%2Bsheet%2Bset%2Caps%2C144&sr=8-5&th=1 | P29: Not defined | R29: 32
A30: ESS-0027 | B30: Bedrooms | C30: Textiles | D30: Utopia Bedding fitted sheets 6 pack (Queen Size) | E30: Amazon | F30: 2 | G30: 51.99 | H30: =IF(OR(F30="",G30=""),0,F30*G30) -> 103.98 | I30: Experience | J30: Candidate | K30: Needs review | L30: Furnishing order | M30: Initial and recurring | N30: https://www.amazon.com/Utopia-Bedding-Queen-Fitted-Sheets/dp/B0C4MLW7D9/ref=dp_prsubs_d_sccl_1/147-6591985-7389022?pd_rd_w=f9c2S&content-id=amzn1.sym.be3a2f09-77ee-4ba3-b2da-1b73c76c3fe2&pf_rd_p=be3a2f09-77ee-4ba3-b2da-1b73c76c3fe2&pf_rd_r=SR6HPF2TD5Q1BK633WC3&pd_rd_wg=WNdIL&pd_rd_r=dc58a7b3-0cbb-488e-91c1-6ff05ba531ff&pd_rd_i=B0C4MLW7D9&th=1 | P30: Not defined | R30: 33
... A114: ESS-0114 | B114: Miscellaneous | C114: Technology & Safety | D114: Flashlight | E114: Walmart | F114: 1 | G114: 4.97 | H114: =IF(OR(F114="",G114=""),0,F114*G114) -> 4.97 | I114: Operational | J114: Candidate | K114: Needs review | L114: Furnishing order | M114: Initial setup only | N114: https://www.walmart.com/ip/Ozark-Trail-500-Lumen-3AAA-LED-Flashlight/18121018841?classType=REGULAR&athbdg=L1600&from=/search | P114: Not defined | R114: 126

Sheet Gap Register
A1: Essentials — Sourcing Gap Register
A3: Gap ID | B3: Room | C3: Requirement | D3: Priority | E3: Quantity | F3: Action Needed | G3: Requirement State | H3: Sourcing Status | I3: Estimated Cost
A4: GAP-001 | B4: Living Room | C4: TV surge protector | D4: Launch-critical | E4: 1 | F4: https://www.amazon.com/Charger-Protector-QINLIANF-Extender-Charging/dp/B08R6T1M9T?tag=lifewire-paid-20&ascsubtag=11712201%7C%7C%7C%7C%7C%7Cpc&th=1 | G4: Required | H4: Needs review | I4: 19.99
A5: GAP-002 | B5: Living Room | C5: TV cable-management kit | D5: Operational | E5: 1 | F5: https://www.walmart.com/ip/Cord-Hider-Delamu-31-4-Cord-Cover-Large-PVC-Wire-Cable-Hider-for-Wall-Mounted-TV-White/634148719?wmlspartner=wlpa&selectedSellerId=101073679&selectedOfferId=91121EF9C4944C0AB4DFC75C86387EAF&conditionGroupCode=1&sourceid=dsn_gdn_0c92c416-dbd6-42ec-845c-ecf69af2153d&veh=dsn&wmlspartner=dsn_gdn_0c92c416-dbd6-42ec-845c-ecf69af2153d&cn=0042_fy27_mp_mpa_lo_int_dis_pmax-p13n&wl0=&wl1=g&wl2=c&wl3=&wl4=&wl5=9027296&wl6=&wl7=&wl8=&wl9=pla&wl10=479410972&wl11=online&wl12=91121EF9C4944C0AB4DFC75C86387EAF&gclsrc=aw.ds&gad_source=1&gad_campaignid=23148469844&gbraid=0AAAAADmfBIocJf8YW8QOBZcx1GCJBtAZ_&gclid=Cj0KCQjw16_UBhCqARIsAIdOaXwzIyumOB5atjOeQw2Xh8G_UioBeGYJdg5EyqcjpcoJPx4KUp-OMOAaAkTXEALw_wcB | G5: Required | H5: Needs review | I5: 8.99
A6: GAP-003 | B6: Primary Bedroom | C6: TV surge protector | D6: Launch-critical | E6: 1 | F6: https://www.amazon.com/Charger-Protector-QINLIANF-Extender-Charging/dp/B08R6T1M9T?tag=lifewire-paid-20&ascsubtag=11712201%7C%7C%7C%7C%7C%7Cpc&th=1 | G6: Required | H6: Needs review | I6: 19.99
A7: GAP-004 | B7: Primary Bedroom | C7: TV cable-management kit | D7: Operational | E7: 1 | F7: https://www.walmart.com/ip/Cord-Hider-Delamu-31-4-Cord-Cover-Large-PVC-Wire-Cable-Hider-for-Wall-Mounted-TV-White/634148719?wmlspartner=wlpa&selectedSellerId=101073679&selectedOfferId=91121EF9C4944C0AB4DFC75C86387EAF&conditionGroupCode=1&sourceid=dsn_gdn_0c92c416-dbd6-42ec-845c-ecf69af2153d&veh=dsn&wmlspartner=dsn_gdn_0c92c416-dbd6-42ec-845c-ecf69af2153d&cn=0042_fy27_mp_mpa_lo_int_dis_pmax-p13n&wl0=&wl1=g&wl2=c&wl3=&wl4=&wl5=9027296&wl6=&wl7=&wl8=&wl9=pla&wl10=479410972&wl11=online&wl12=91121EF9C4944C0AB4DFC75C86387EAF&gclsrc=aw.ds&gad_source=1&gad_campaignid=23148469844&gbraid=0AAAAADmfBIocJf8YW8QOBZcx1GCJBtAZ_&gclid=Cj0KCQjw16_UBhCqARIsAIdOaXwzIyumOB5atjOeQw2Xh8G_UioBeGYJdg5EyqcjpcoJPx4KUp-OMOAaAkTXEALw_wcB | G7: Required | H7: Needs review | I7: 8.99
A8: GAP-005 | B8: Second Bedroom | C8: TV surge protector | D8: Launch-critical | E8: 1 | F8: https://www.amazon.com/Charger-Protector-QINLIANF-Extender-Charging/dp/B08R6T1M9T?tag=lifewire-paid-20&ascsubtag=11712201%7C%7C%7C%7C%7C%7Cpc&th=1 | G8: Required | H8: Needs review | I8: 19.99
A9: GAP-006 | B9: Second Bedroom | C9: TV cable-management kit | D9: Operational | E9: 1 | F9: https://www.walmart.com/ip/Cord-Hider-Delamu-31-4-Cord-Cover-Large-PVC-Wire-Cable-Hider-for-Wall-Mounted-TV-White/634148719?wmlspartner=wlpa&selectedSellerId=101073679&selectedOfferId=91121EF9C4944C0AB4DFC75C86387EAF&conditionGroupCode=1&sourceid=dsn_gdn_0c92c416-dbd6-42ec-845c-ecf69af2153d&veh=dsn&wmlspartner=dsn_gdn_0c92c416-dbd6-42ec-845c-ecf69af2153d&cn=0042_fy27_mp_mpa_lo_int_dis_pmax-p13n&wl0=&wl1=g&wl2=c&wl3=&wl4=&wl5=9027296&wl6=&wl7=&wl8=&wl9=pla&wl10=479410972&wl11=online&wl12=91121EF9C4944C0AB4DFC75C86387EAF&gclsrc=aw.ds&gad_source=1&gad_campaignid=23148469844&gbraid=0AAAAADmfBIocJf8YW8QOBZcx1GCJBtAZ_&gclid=Cj0KCQjw16_UBhCqARIsAIdOaXwzIyumOB5atjOeQw2Xh8G_UioBeGYJdg5EyqcjpcoJPx4KUp-OMOAaAkTXEALw_wcB | G9: Required | H9: Needs review | I9: 8.99
A10: GAP-007 | B10: Primary Bedroom | C10: Dresser or wardrobe | D10: Operational | E10: 1 | F10: https://www.walmart.com/ip/HODYANN-Portable-Closet-Wardrobe-Closet-6-Storage-Shelves-2-Hanging-Rods-Non-Woven-Fabric-Cover-34-6-x-17-7-66-1-Inches-Organizer-Bedroom-Gray/17323303546?wmlspartner=wlpa&selectedSellerId=101187780&selectedOfferId=C1F8DDFDDAFC3693A8BA05058ECF2273&conditionGroupCode=1&gclsrc=aw.ds&&adid=22222222227C1F8DDFDDAFC3693A8BA05058ECF2273_200921946602_24153394724&wl0=&wl1=g&wl2=c&wl3=821367569901&wl4=pla-2444379397870&wl5=9027296&wl6=&wl7=&wl8=&wl9=pla&wl10=765412572&wl11=online&wl12=C1F8DDFDDAFC3693A8BA05058ECF2273&veh=sem&gad_source=1&gad_campaignid=24153394724&gbraid=0AAAABDAnf96LmG27oLniUmN1PzXdM-VVX&gclid=Cj0KCQjw16_UBhCqARIsAIdOaXwXmZCZiEOXfpMdTDTLO9yapxIU3gSpgzE4SeDU5rsB-y_Ir837mlQaAtYrEALw_wcB | G10: Required | H10: Needs review | I10: 25.64
A11: GAP-008 | B11: Second Bedroom | C11: Dresser or wardrobe | D11: Operational | E11: 1 | F11: https://www.walmart.com/ip/HODYANN-Portable-Closet-Wardrobe-Closet-6-Storage-Shelves-2-Hanging-Rods-Non-Woven-Fabric-Cover-34-6-x-17-7-66-1-Inches-Organizer-Bedroom-Gray/17323303546?wmlspartner=wlpa&selectedSellerId=101187780&selectedOfferId=C1F8DDFDDAFC3693A8BA05058ECF2273&conditionGroupCode=1&gclsrc=aw.ds&&adid=22222222227C1F8DDFDDAFC3693A8BA05058ECF2273_200921946602_24153394724&wl0=&wl1=g&wl2=c&wl3=821367569901&wl4=pla-2444379397870&wl5=9027296&wl6=&wl7=&wl8=&wl9=pla&wl10=765412572&wl11=online&wl12=C1F8DDFDDAFC3693A8BA05058ECF2273&veh=sem&gad_source=1&gad_campaignid=24153394724&gbraid=0AAAABDAnf96LmG27oLniUmN1PzXdM-VVX&gclid=Cj0KCQjw16_UBhCqARIsAIdOaXwXmZCZiEOXfpMdTDTLO9yapxIU3gSpgzE4SeDU5rsB-y_Ir837mlQaAtYrEALw_wcB | G11: Required | H11: Needs review | I11: 25.64
A12: GAP-009 | B12: Primary Bedroom | C12: Practical dressing mirror | D12: Experience | E12: 1 | F12: https://www.walmart.com/ip/BLACK-GALLERY-OTD/14609716185 | G12: Required | H12: Needs review | I12: 14.92
A13: GAP-010 | B13: Second Bedroom | C13: Practical dressing mirror | D13: Experience | E13: 1 | F13: https://www.walmart.com/ip/BLACK-GALLERY-OTD/14609716185 | G13: Required | H13: Needs review | I13: 14.92
A14: GAP-011 | B14: Primary Bedroom | C14: Luggage rack | D14: Operational | E14: 1 | F14: https://www.walmart.com/ip/SONGMICS-Luggage-Racks-Set-of-2-Suitcase-Stand-with-Fabric-Storage-Shelf-for-Guest-Room-Bedroom-Hotel-Foldable-Holds-up-to-110-lb-Black/3436867722?wmlspartner=wlpa&selectedSellerId=101068213&selectedOfferId=FC0881491E1846B79773F748FC0A4588&conditionGroupCode=1&adid=22222222227FC0881491E1846B79773F748FC0A4588_186603386549_23034149881&wl0=&wl1=g&wl2=c&wl3=779198807195&wl4=pla-2444484496258&wl5=9027296&wl6=&wl7=&wl8=&wl9=pla&wl10=382394450&wl11=online&wl12=FC0881491E1846B79773F748FC0A4588&veh=sem&gad_source=1&gad_campaignid=23034149881&gbraid=0AAAABDAnf97NV0cpAnztr1FsIW9UtU5A_&gclid=Cj0KCQjw16_UBhCqARIsAIdOaXx6s9XZXneJlIe9SjqKAG6UPg0sIfmxI_oQ-Omlojj-EeYr9mJb6B8aApjDEALw_wcB | G14: Required | H14: Needs review | I14: 35.99
A15: GAP-012 | B15: Workspace | C15: Task lamp | D15: Operational | E15: 1 | F15: https://www.walmart.com/ip/LED-Desk-Lamp-Dimmable-Desk-Light-Table-Lamp-Black/17707666750?classType=REGULAR&from=/search | G15: Required | H15: Needs review | I15: 18.69
... A24: GAP-021 | B24: Dining Room | C24: Table Runner | D24: Operational | E24: 1 | F24: https://www.walmart.com/ip/Sm-e-Sage-Green-Table-Runner-13x72-Inch-Seasonal-Washable-Kitchen-Dining-Table-Decoration-for-Home-Party/16468020336?wmlspartner=wlpa&selectedSellerId=101090365&selectedOfferId=D3F3FF6ADE14322EA3E6470B19730A60&conditionGroupCode=1&sourceid=dsn_gdn_0c92c416-dbd6-42ec-845c-ecf69af2153d&veh=dsn&wmlspartner=dsn_gdn_0c92c416-dbd6-42ec-845c-ecf69af2153d&cn=0042_fy27_mp_mpa_lo_int_dis_pmax-p13n&wl0=&wl1=g&wl2=c&wl3=&wl4=&wl5=9027296&wl6=&wl7=&wl8=&wl9=pla&wl10=466096436&wl11=online&wl12=D3F3FF6ADE14322EA3E6470B19730A60&gclsrc=aw.ds&gad_source=1&gad_campaignid=23148469844&gbraid=0AAAAADmfBIocJf8YW8QOBZcx1GCJBtAZ_&gclid=Cj0KCQjw16_UBhCqARIsAIdOaXyV5J1UCF0r16dzAygnb6kaFBh35f3vNYY49bsg8i0RCmdA8EQSv4EaAuRKEALw_wcB | G24: Required | H24: Needs review | I24: 8.49

Sheet Room Standards
A1: Approved Essentials Baseline
A3: Standard | B3: Approved Decision | C3: Operational Note
A4: Property | B4: 2-bedroom / 2-bath | C4: Approved baseline
A5: Occupancy | B5: 6 guests | C5: Two queen beds + queen sleeper sofa
A6: Style | B6: Warm modern | C6: Warm woods, soft neutrals, black/aged-brass accents
A7: Budget target | B7: $11000-$14000 | C7: Products and delivery
A8: Flexibility ceiling | B8: $15,500 | C8: Tax, assembly, installation, mounting labor and service fees excluded
A9: Living room | B9: Sleeper sofa; seating for 5; 55–65 in TV; mount; console; tables; lighting; rug; décor | C9: TV package includes surge protection and cable management
A10: Primary bedroom | B10: Queen bed; mattress; storage; bedside surfaces/lights; TV/mount; charging; mirror; luggage support | C10: Two-sided bed access where feasible
A11: Second bedroom | B11: Queen bed; mattress; storage; bedside surfaces/lights; TV/mount; charging; mirror; luggage support | C11: Same functional standard as primary
A12: Dining | B12: Seating for 6 | C12: Normal use cannot depend on stored leaves
A13: Kitchen | B13: Place settings for 8; essential cookware and small appliances | C13: Durable and simple guest operation
A14: Bathrooms | B14: Two towel sets per guest; hair dryers; bath mats; storage; utility items | C14: Operating consumables tracked separately
A15: Workspace | B15: Real desk; supportive chair; task light; grounded power; charging; waste bin | C15: Not a decorative console

Sheet Vendors
A1: Vendor Directory
A3: Vendor ID | B3: Vendor | C3: Ordering Mode | D3: Primary Role | E3: Launch Status
A4: VEN-COSTCO | B4: Costco | C4: assisted_ordering | D4: Mattresses, selected furniture, TVs, appliances, durable goods | E4: Approved launch retailer
A5: VEN-WALMART | B5: Walmart | C5: assisted_ordering | D5: Bedding, bath, kitchen, utility, rapid replacements | E5: Approved launch retailer
A6: VEN-AMAZON | B6: Amazon | C6: assisted_ordering | D6: Kitchen, lighting, technology, safety, exact-spec products | E6: Avoid unverified marketplace sellers
A7: VEN-WAYFAIR | B7: Wayfair | C7: assisted_ordering | D7: Sleeper sofas, accent furniture, rugs, lighting, alternatives | E7: Approved launch retailer
A8: VEN-IKEA | B8: IKEA | C8: assisted_ordering | D8: Beds, storage, dining, workspace, replacement-friendly furniture | E8: Approved launch retailer
A9: VEN-LOWES | B9: Lowe's | C9: external_order_recording | D9: Legacy source only | E9: Replace in launch catalog
A10: VEN-KOHLS | B10: Kohl's | C10: external_order_recording | D10: Legacy source only | E10: Replace in launch catalog

Sheet Source Reference
A1: Source Workbook Reference
A3: Source Sheet | B3: Source Row | C3: Section | D3: Item | E3: Source URL | F3: Source Note
A4: Consolidated | B4: 5 | C4: Living Room | D4: Side Table | E4: https://www.amazon.com/dp/B0CL4QPXQK/?coliid=I1K94TQBE6CKMP&colid=1M4ZRDEJBTOSI&th=1 | F4: Imported as a seed candidate; not price/availability verified
A5: Consolidated | B5: 6 | C5: Living Room | D5: TV stand | E5: https://www.walmart.com/ip/River-Street-Designs-Sage-52-Metal-Frame-TV-Stand-Natural-Black/444185047?classType=REGULAR | F5: Imported as a seed candidate; not price/availability verified
A6: Consolidated | B6: 7 | C6: Living Room | D6: Dining Table | E6: https://www.lowes.com/pd/Garvee-Dining-Table-Set-for-4-with-Storage-Rack-Kitchen-Table-and-Upholstered-Chairs-of-4-Wood-Tabletop-and-Heavy-Duty-Metel-Frame-Dining-Room-Set-for-Small-Space-Apartment-Brown/5017826543?user=shopping&feed=yes&utm_source=chatgpt.com | F6: Imported as a seed candidate; not price/availability verified
A7: Consolidated | B7: 8 | C7: Living Room | D7: Ring Doorbell Kit (wireless) | E7: https://www.amazon.com/dp/B09WZBPX7K/?coliid=I3L5N7BZGIHVZW&colid=1M4ZRDEJBTOSI&th=1 | F7: Imported as a seed candidate; not price/availability verified
A8: Consolidated | B8: 9 | C8: Living Room | D8: Schalge Encode | E8: https://www.amazon.com/dp/B07HXFKMYR/?coliid=I5BG3QRC5EMKU&colid=1M4ZRDEJBTOSI&th=1 | F8: Imported as a seed candidate; not price/availability verified
A9: Consolidated | B9: 10 | C9: Living Room | D9: TV Mount | E9: None | F9: Imported as a seed candidate; not price/availability verified
A10: Consolidated | B10: 11 | C10: Living Room | D10: Coffee Table | E10: https://www.amazon.com/dp/B0CL4QPXQK/?coliid=I1K94TQBE6CKMP&colid=1M4ZRDEJBTOSI&th=1 | F10: Imported as a seed candidate; not price/availability verified
A11: Consolidated | B11: 12 | C11: Living Room | D11: 50 inch Smart TV | E11: https://www.walmart.com/ip/seot/300694285?listRegistryId=5b62a874-18a6-4aa7-ae38-49a6da8ee6d7&listRegistryType=WL | F11: Imported as a seed candidate; not price/availability verified
A12: Consolidated | B12: 13 | C12: Living Room | D12: Throw Pillows 20x20 (set of 2) | E12: https://www.walmart.com/ip/seot/12769156945?listRegistryId=5b62a874-18a6-4aa7-ae38-49a6da8ee6d7&listRegistryType=WL | F12: Imported as a seed candidate; not price/availability verified
A13: Consolidated | B13: 14 | C13: Living Room | D13: Sofa | E13: https://www.walmart.com/ip/seot/9130900014?listRegistryId=e0137f6c-0e2c-4ff6-803f-31d87046ce07&listRegistryType=WL | F13: Imported as a seed candidate; not price/availability verified
A14: Consolidated | B14: 15 | C14: Living Room | D14: Lamps | E14: https://www.walmart.com/ip/seot/5013201859?listRegistryId=e6b42c31-c60b-4a7a-b67b-0ae06309ed95&listRegistryType=WL | F14: Imported as a seed candidate; not price/availability verified
A15: Consolidated | B15: 16 | C15: Living Room | D15: Fake plants | E15: https://www.walmart.com/ip/DR-Planzen-5-feet-Artificial-Ficus-Tree-Lifelike-Greenery-Natural-Wood-Trunk-Living-Room-office-floor-corner-decor-Tall-Indoor-Artificial-Trees-Black/2805424764 | F15: Imported as a seed candidate; not price/availability verified
... A17: Consolidated | B17: 18 | C17: Living Room | D17: Wall Art | E17: IDEA4WALL Mid Century Shape Brown Faded Black Abstract Modern Pictures Framed 2 Pieces Canvas Print Wall Art & Reviews | Wayfair | F17: Imported as a seed candidate; not price/availability verified
A18: Consolidated | B18: 19 | C18: Living Room | D18: Small Décor | F18: Imported as a seed candidate; not price/availability verified
A19: Consolidated | B19: 20 | C19: Living Room | D19: Accent Chair | E19: https://www.walmart.com/ip/seot/8473020072?listRegistryId=e0137f6c-0e2c-4ff6-803f-31d87046ce07&listRegistryType=WL | F19: Imported as a seed candidate; not price/availability verified
A20: Consolidated | B20: 23 | C20: Bedrooms | D20: Queen Bed Frame | E20: https://www.amazon.com/dp/B086M58PQ3/?coliid=I8MFC9QO4PAK4&colid=1VYLQVL2D6O92&th=1 | F20: Imported as a seed candidate; not price/availability verified
A21: Consolidated | B21: 24 | C21: Bedrooms | D21: Queen 10 inch Memory Foam | E21: https://www.amazon.com/dp/B0CSJQGDC6/?coliid=I3RMXVUSK9XBCN&colid=1VYLQVL2D6O92&th=1 | F21: Imported as a seed candidate; not price/availability verified
A22: Consolidated | B22: 25 | C22: Bedrooms | D22: 50 inch Smart TV | E22: https://www.walmart.com/ip/seot/300694285?listRegistryId=5b62a874-18a6-4aa7-ae38-49a6da8ee6d7&listRegistryType=WL | F22: Imported as a seed candidate; not price/availability verified
A23: Consolidated | B23: 26 | C23: Bedrooms | D23: TV Mount | E23: https://www.walmart.com/ip/Full-Motion-Articulating-TV-Wall-Mount-Bracket-Swivel-Tilting-Fits-26-65-Inch-Flat-Curved-TVs-Holds-up-to-99lbs/148790691?wmlspartner=wlpa&selectedSellerId=102594905&selectedOfferId=C3BA38E0BCA2329986317E165F8874BC&conditionGroupCode=1&gclsrc=aw.ds&&adid=22222222227C3BA38E0BCA2329986317E165F8874BC_198068869633_23857841887&wl0=&wl1=g&wl2=c&wl3=809139801293&wl4=pla-2483468578281&wl5=9027296&wl6=&wl7=&wl8=&wl9=pla&wl10=5469150719&wl11=online&wl12=C3BA38E0BCA2329986317E165F8874BC&veh=sem&gad_source=1&gad_campaignid=23857841887&gbraid=0AAAABDAnf97DbT-I179GyN1uuWAMb62nN&gclid=Cj0KCQjwm8bTBhDWARIsAC9Hi8lce0YQZUmNpxDX2e9gkBK3LFY_UtxkoHi526hlhVNuNG_bI9quDyUaAokCEALw_wcB | F23: Imported as a seed candidate; not price/availability verified
A24: Consolidated | B24: 27 | C24: Bedrooms | D24: Nightstand | E24: https://www.walmart.com/ip/Mainstays-2-Drawer-Fabric-Nightstand-Brown-MDF-Front/5408951480 | F24: Imported as a seed candidate; not price/availability verified
A25: Consolidated | B25: 28 | C25: Bedrooms | D25: Nightstand Lamp | E25: https://www.lowes.com/pd/BIGHOUSE-2-Pack-Touch-Control-Small-Table-Lamp-Set-With-USB-A-C-Charging-Ports-3-Way-Dimmable-Texture-Oatmeal-Linen-Shade-14-25-Inch-LED-Bulb-Included/5017067475 | F25: Imported as a seed candidate; not price/availability verified
A26: Consolidated | B26: 29 | C26: Bedrooms | D26: Blackout Curtains (check room for correct size) | E26: https://www.amazon.com/dp/B09HBXQTLJ/?coliid=I2FDKI5OGXR160&colid=1VYLQVL2D6O92&th=1 | F26: Imported as a seed candidate; not price/availability verified
A27: Consolidated | B27: 30 | C27: Bedrooms | D27: Wooden hangers - 20pk | E27: https://www.amazon.com/High-Grade-Hangers-Smooth-Precisely-Camisole/dp/B075FBQB2W/ref=sr_1_1_sspa?crid=FZHEWKOAQ0CU&keywords=wooden+hangers&qid=1671226028&sprefix=wooden+%2Caps%2C664&sr=8-1-spons&psc=1&spLa=ZW5jcnlwdGVkUXVhbGlmaWVyPUEzSUdYSzVQMDJBWUVLJmVuY3J5cHRlZElkPUEwNjM5NzI2M0tUQkFDQ0xOUDlXRCZlbmNyeXB0ZWRBZElkPUEwODI0NTEwMlYwRDJYS1MzMDFBRyZ3aWRnZXROYW1lPXNwX2F0ZiZhY3Rpb249Y2xpY2tSZWRpcmVjdCZkb05vdExvZ0NsaWNrPXRydWU= | F27: Imported as a seed candidate; not price/availability verified
A28: Consolidated | B28: 31 | C28: Bedrooms | D28: Curtain rod - wrap around (check room for correct size) | E28: https://www.amazon.com/AmazonBasics-Room-Darkening-Curtain-Rod-Bronze/dp/B0792JTC66/ref=sr_1_1_sspa?crid=27WLJUKEZWKD&keywords=curtain%2Brod%2Bwrap%2Baround&qid=1671226100&sprefix=curtain%2Brod%2Bwrap%2Baround%2Caps%2C128&sr=8-1-spons&spLa=ZW5jcnlwdGVkUXVhbGlmaWVyPUEzUEQ3MU5HOTlDRUpZJmVuY3J5cHRlZElkPUEwMTU3MTExMlMyOTY1UUg2V0pNNiZlbmNyeXB0ZWRBZElkPUEwNDQxNzkxVU9QOFBJTVY3SkJUJndpZGdldE5hbWU9c3BfYXRmJmFjdGlvbj1jbGlja1JlZGlyZWN0JmRvTm90TG9nQ2xpY2s9dHJ1ZQ&th=1 | F28: Imported as a seed candidate; not price/availability verified
A29: Consolidated | B29: 32 | C29: Bedrooms | D29: Utopia Bedding flat sheets 6 pack(Queen Size) | E29: https://www.amazon.com/Flat-Sheet-White-Brushed-Microfiber/dp/B00XK9CN3U/ref=sr_1_5?crid=1MFHWYB1ZK2TH&keywords=utopia%2Bflat%2Bsheet%2Bset&qid=1671226149&sprefix=utopia%2Bflat%2Bsheet%2Bset%2Caps%2C144&sr=8-5&th=1 | F29: Imported as a seed candidate; not price/availability verified
A30: Consolidated | B30: 33 | C30: Bedrooms | D30: Utopia Bedding fitted sheets 6 pack (Queen Size) | E30: https://www.amazon.com/Utopia-Bedding-Queen-Fitted-Sheets/dp/B0C4MLW7D9/ref=dp_prsubs_d_sccl_1/147-6591985-7389022?pd_rd_w=f9c2S&content-id=amzn1.sym.be3a2f09-77ee-4ba3-b2da-1b73c76c3fe2&pf_rd_p=be3a2f09-77ee-4ba3-b2da-1b73c76c3fe2&pf_rd_r=SR6HPF2TD5Q1BK633WC3&pd_rd_wg=WNdIL&pd_rd_r=dc58a7b3-0cbb-488e-91c1-6ff05ba531ff&pd_rd_i=B0C4MLW7D9&th=1 | F30: Imported as a seed candidate; not price/availability verified
... A117: Consolidated | B117: 126 | C117: Miscellaneous | D117: Flashlight | E117: https://www.walmart.com/ip/Ozark-Trail-500-Lumen-3AAA-LED-Flashlight/18121018841?classType=REGULAR&athbdg=L1600&from=/search | F117: Imported as a seed candidate; not price/availability verified

Sheet Data Dictionary
A1: Catalog Data Dictionary
A3: Field | B3: Definition | C3: Required for procurement | D3: Controlled values / rule
A4: Product ID | B4: Stable internal identifier | C4: Yes | D4: ESS-####
A5: Room | B5: Primary room assignment | C5: Yes | D5: Living Room, Bedroom, Dining, Kitchen, Bathroom, Workspace, Entry, Project
A6: Category | B6: Governed product taxonomy | C6: Yes | D6: Furniture, Textiles, Lighting, Technology & Safety, etc.
A7: Retailer | B7: Current source retailer | C7: Yes | D7: Approved launch retailers preferred
A8: Extended Cost | B8: Quantity multiplied by unit price | C8: Yes | D8: Formula-driven
A9: Source Status | B9: Quality of imported source line | C9: Yes | D9: Candidate, Incomplete, Replace retailer, Replace specification
A10: Review Status | B10: Todd's catalog decision | C10: Yes | D10: Approve, alternative, Replace, Hold, Reject
A11: Procurement Class | B11: Separates furnishings from replenishable supplies | C11: Yes | D11: Furnishing order, Operating supply
A12: Variant / Specifications | B12: Exact size, finish, color, model and SKU | C12: Yes before order | D12: Free text until canonical variant table is activated
A13: Substitution | B13: Allowed substitution policy | C13: Yes | D13: Controlled values in Catalog Review
A14: Last Verified | B14: Last price/availability check | C14: Yes before order | D14: Date
